astar_math/__init__.py
astar_math/curve/__init__.py
astar_math/curve/bezier.py
astar_math/curve/catmull_rom.py
astar_math/functions/__init__.py
astar_math/functions/_function_class.py
astar_math/functions/_functions.py
astar_math/functions/_intervals.py
astar_math/fuzzy/__init__.py
astar_math/fuzzy/core.py
astar_math/fuzzy/functions.py
astar_math/fuzzy/intervals.py
astar_math/fuzzy/matrix.py
astar_math/fuzzy/number.py
astar_math/lie/__init__.py
astar_math/lie/algebra.py
astar_math/lie/group.py
astar_math/lie/lie.py
astar_math/lie/matrix.py
astar_math/linear_algebra/__init__.py
astar_math/linear_algebra/matrix.py
astar_math/linear_algebra/retate.py
astar_math/numbers/__init__.py
astar_math/numbers/_complex.py
astar_math/optimize/__init__.py
astar_math/optimize/_optimize.py
astar_math/plot/__init__.py
astar_math/plot/plot_function.py
astar_math/random/__init__.py
astar_math/random/random.py
astar_math/special/__init__.py
astar_math/special/_special.py
astar_math/test/__init__.py
astar_math/test/test_function.py
astar_math/test/test_fuzzy.py
astar_math/test/test_intervals.py
astar_math/test/test_matrix.py
astar_math/test/test_numbers.py
astar_math/test/test_optimize.py
astar_math/test/test_special.py
astar_math/test/test_wu_method.py
astar_math/test/test_functions/__init__.py
astar_math/test/test_functions/test_function.py
astar_math/test/test_functions/test_function_class.py
astar_math/test/test_functions/test_intervals.py
astar_math-0.2.dist-info/LICENSE
astar_math-0.2.dist-info/METADATA
astar_math-0.2.dist-info/WHEEL
astar_math-0.2.dist-info/top_level.txt
astar_math-0.2.dist-info/RECORD
