Metadata-Version: 2.1
Name: astar-math
Version: 0.2
Summary: Python math
Home-page: https://gitee.com/hoops/astar-mathtool
Author: A.Star
Author-email: astar@snowland.ltd
Maintainer: A.Star
Maintainer-email: astar@snowland.ltd
License: Apache v2.0 License
Platform: all
Classifier: Operating System :: OS Independent
Classifier: Intended Audience :: Developers
Classifier: License :: OSI Approved :: Apache Software License
Classifier: Programming Language :: Python
Classifier: Programming Language :: Python :: Implementation
Classifier: Programming Language :: Python :: 2
Classifier: Programming Language :: Python :: 2.7
Classifier: Programming Language :: Python :: 3
Classifier: Programming Language :: Python :: 3.6
Classifier: Programming Language :: Python :: 3.7
Classifier: Programming Language :: Python :: 3.8
Classifier: Programming Language :: Python :: 3.9
Classifier: Programming Language :: Python :: 3.10
Classifier: Programming Language :: Python :: 3.11
Classifier: Programming Language :: Python :: 3.12
Classifier: Programming Language :: Python :: 3.13
Classifier: Topic :: Software Development :: Libraries
License-File: LICENSE
Requires-Dist: astartool (>=0.1.0)
Requires-Dist: astar-devopstool (>=0.0.7)
Requires-Dist: numpy
Requires-Dist: scipy
Requires-Dist: liepack
Requires-Dist: matplotlib
